{
  "turns": {
    "1": [
      {
        "action": "build",
        "at": [
          39,
          8
        ]
      }
    ],
    "2": [
      {
        "action": "build",
        "at": [
          39,
          6
        ]
      },
      {
        "action": "move_to",
        "to": [
          39,
          6
        ]
      }
    ],
    "3": [
      {
        "action": "build",
        "at": [
          38,
          6
        ]
      }
    ],
    "4": [
      {
        "action": "move_to",
        "to": [
          40,
          7
        ]
      }
    ],
    "5": [
      {
        "action": "move_to",
        "to": [
          39,
          8
        ]
      }
    ],
    "6": [
      {
        "action": "build",
        "at": [
          39,
          9
        ]
      }
    ],
    "7": [
      {
        "action": "move_to",
        "to": [
          40,
          9
        ]
      }
    ],
    "8": [
      {
        "action": "build",
        "at": [
          41,
          10
        ]
      }
    ],
    "9": [
      {
        "action": "move_to",
        "to": [
          41,
          10
        ]
      }
    ],
    "10": [
      {
        "action": "build",
        "at": [
          41,
          11
        ]
      },
      {
        "action": "move_to",
        "to": [
          41,
          11
        ]
      }
    ],
    "11": [
      {
        "action": "move_to",
        "to": [
          41,
          12
        ]
      }
    ],
    "12": [
      {
        "action": "build",
        "at": [
          41,
          13
        ]
      }
    ],
    "13": [
      {
        "action": "move_to",
        "to": [
          41,
          11
        ]
      }
    ],
    "14": [
      {
        "action": "move_to",
        "to": [
          41,
          10
        ]
      }
    ],
    "15": [
      {
        "action": "move_to",
        "to": [
          40,
          9
        ]
      }
    ],
    "16": [
      {
        "action": "move_to",
        "to": [
          39,
          8
        ]
      }
    ],
    "17": [
      {
        "action": "build",
        "at": [
          38,
          8
        ]
      }
    ],
    "18": [
      {
        "action": "build",
        "at": [
          38,
          9
        ]
      }
    ],
    "19": [
      {
        "action": "move_to",
        "to": [
          38,
          8
        ]
      }
    ],
    "20": [
      {
        "action": "build",
        "at": [
          37,
          9
        ]
      }
    ],
    "21": [
      {
        "action": "move_to",
        "to": [
          39,
          8
        ]
      }
    ],
    "22": [
      {
        "action": "move_to",
        "to": [
          40,
          9
        ]
      }
    ],
    "23": [
      {
        "action": "move_to",
        "to": [
          41,
          10
        ]
      }
    ],
    "24": [
      {
        "action": "move_to",
        "to": [
          41,
          11
        ]
      }
    ],
    "25": [
      {
        "action": "move_to",
        "to": [
          41,
          12
        ]
      }
    ],
    "26": [
      {
        "action": "build",
        "at": [
          42,
          13
        ]
      },
      {
        "action": "move_to",
        "to": [
          42,
          13
        ]
      }
    ],
    "27": [
      {
        "action": "move_to",
        "to": [
          41,
          14
        ]
      }
    ],
    "28": [
      {
        "action": "build",
        "at": [
          42,
          15
        ]
      }
    ],
    "29": [
      {
        "action": "move_to",
        "to": [
          42,
          15
        ]
      }
    ],
    "30": [
      {
        "action": "move_to",
        "to": [
          42,
          16
        ]
      }
    ],
    "31": [
      {
        "action": "move_to",
        "to": [
          41,
          17
        ]
      }
    ],
    "32": [
      {
        "action": "move_to",
        "to": [
          40,
          18
        ]
      }
    ],
    "33": [
      {
        "action": "move_to",
        "to": [
          41,
          19
        ]
      }
    ],
    "34": [
      {
        "action": "build",
        "at": [
          42,
          20
        ]
      }
    ],
    "35": [
      {
        "action": "move_to",
        "to": [
          41,
          20
        ]
      }
    ],
    "36": [
      {
        "action": "build",
        "at": [
          41,
          21
        ]
      }
    ],
    "37": [
      {
        "action": "build",
        "at": [
          42,
          21
        ]
      }
    ],
    "38": [
      {
        "action": "move_to",
        "to": [
          41,
          19
        ]
      }
    ],
    "39": [
      {
        "action": "move_to",
        "to": [
          40,
          18
        ]
      }
    ],
    "40": [
      {
        "action": "move_to",
        "to": [
          41,
          17
        ]
      }
    ],
    "41": [
      {
        "action": "move_to",
        "to": [
          42,
          16
        ]
      }
    ],
    "42": [
      {
        "action": "move_to",
        "to": [
          42,
          15
        ]
      }
    ],
    "43": [
      {
        "action": "move_to",
        "to": [
          41,
          14
        ]
      }
    ],
    "44": [
      {
        "action": "move_to",
        "to": [
          42,
          13
        ]
      }
    ],
    "45": [
      {
        "action": "move_to",
        "to": [
          41,
          12
        ]
      }
    ],
    "46": [
      {
        "action": "move_to",
        "to": [
          41,
          11
        ]
      }
    ],
    "47": [
      {
        "action": "move_to",
        "to": [
          41,
          10
        ]
      }
    ],
    "48": [
      {
        "action": "move_to",
        "to": [
          40,
          9
        ]
      }
    ],
    "49": [
      {
        "action": "move_to",
        "to": [
          39,
          8
        ]
      }
    ],
    "50": [
      {
        "action": "move_to",
        "to": [
          40,
          7
        ]
      }
    ],
    "51": [
      {
        "action": "build",
        "at": [
          41,
          6
        ]
      }
    ],
    "52": [
      {
        "action": "move_to",
        "to": [
          39,
          8
        ]
      }
    ],
    "53": [
      {
        "action": "move_to",
        "to": [
          40,
          9
        ]
      }
    ],
    "54": [
      {
        "action": "move_to",
        "to": [
          41,
          10
        ]
      }
    ],
    "55": [
      {
        "action": "move_to",
        "to": [
          41,
          11
        ]
      }
    ],
    "56": [
      {
        "action": "move_to",
        "to": [
          41,
          12
        ]
      }
    ],
    "57": [
      {
        "action": "move_to",
        "to": [
          42,
          13
        ]
      }
    ],
    "58": [
      {
        "action": "move_to",
        "to": [
          41,
          14
        ]
      }
    ],
    "59": [
      {
        "action": "move_to",
        "to": [
          40,
          15
        ]
      }
    ],
    "60": [
      {
        "action": "build",
        "at": [
          39,
          16
        ]
      }
    ],
    "61": [
      {
        "action": "move_to",
        "to": [
          41,
          14
        ]
      }
    ],
    "62": [
      {
        "action": "move_to",
        "to": [
          42,
          13
        ]
      }
    ],
    "63": [
      {
        "action": "build",
        "at": [
          42,
          12
        ]
      }
    ],
    "64": [
      {
        "action": "move_to",
        "to": [
          41,
          14
        ]
      }
    ],
    "65": [
      {
        "action": "move_to",
        "to": [
          42,
          15
        ]
      }
    ],
    "66": [
      {
        "action": "move_to",
        "to": [
          42,
          16
        ]
      }
    ],
    "67": [
      {
        "action": "move_to",
        "to": [
          41,
          17
        ]
      }
    ],
    "68": [
      {
        "action": "move_to",
        "to": [
          40,
          18
        ]
      }
    ],
    "69": [
      {
        "action": "move_to",
        "to": [
          41,
          19
        ]
      }
    ],
    "70": [
      {
        "action": "build",
        "at": [
          40,
          20
        ]
      }
    ],
    "71": [
      {
        "action": "move_to",
        "to": [
          40,
          18
        ]
      }
    ],
    "72": [
      {
        "action": "build",
        "at": [
          39,
          19
        ]
      },
      {
        "action": "move_to",
        "to": [
          39,
          19
        ]
      }
    ],
    "73": [
      {
        "action": "build",
        "at": [
          38,
          20
        ]
      }
    ],
    "74": [
      {
        "action": "build",
        "at": [
          39,
          20
        ]
      },
      {
        "action": "move_to",
        "to": [
          39,
          20
        ]
      }
    ],
    "75": [
      {
        "action": "build",
        "at": [
          39,
          21
        ]
      }
    ],
    "76": [
      {
        "action": "build",
        "at": [
          38,
          21
        ]
      },
      {
        "action": "move_to",
        "to": [
          38,
          21
        ]
      }
    ],
    "77": [
      {
        "action": "build",
        "at": [
          37,
          21
        ]
      }
    ],
    "78": [
      {
        "action": "move_to",
        "to": [
          39,
          20
        ]
      }
    ],
    "79": [
      {
        "action": "move_to",
        "to": [
          39,
          19
        ]
      }
    ],
    "80": [
      {
        "action": "move_to",
        "to": [
          40,
          18
        ]
      }
    ],
    "81": [
      {
        "action": "move_to",
        "to": [
          41,
          17
        ]
      }
    ],
    "82": [
      {
        "action": "move_to",
        "to": [
          42,
          16
        ]
      }
    ],
    "83": [
      {
        "action": "move_to",
        "to": [
          42,
          15
        ]
      }
    ],
    "84": [
      {
        "action": "move_to",
        "to": [
          41,
          14
        ]
      }
    ],
    "85": [
      {
        "action": "move_to",
        "to": [
          42,
          13
        ]
      }
    ],
    "86": [
      {
        "action": "move_to",
        "to": [
          41,
          12
        ]
      }
    ],
    "87": [
      {
        "action": "move_to",
        "to": [
          41,
          11
        ]
      }
    ],
    "88": [
      {
        "action": "move_to",
        "to": [
          41,
          10
        ]
      }
    ],
    "89": [
      {
        "action": "move_to",
        "to": [
          40,
          9
        ]
      }
    ],
    "90": [
      {
        "action": "move_to",
        "to": [
          39,
          8
        ]
      }
    ],
    "91": [
      {
        "action": "move_to",
        "to": [
          38,
          8
        ]
      }
    ],
    "92": [
      {
        "action": "build",
        "at": [
          37,
          8
        ]
      }
    ],
    "93": [
      {
        "action": "move_to",
        "to": [
          39,
          8
        ]
      }
    ],
    "94": [
      {
        "action": "move_to",
        "to": [
          40,
          9
        ]
      }
    ],
    "95": [
      {
        "action": "move_to",
        "to": [
          41,
          10
        ]
      }
    ],
    "96": [
      {
        "action": "move_to",
        "to": [
          41,
          11
        ]
      }
    ],
    "97": [
      {
        "action": "move_to",
        "to": [
          41,
          12
        ]
      }
    ],
    "98": [
      {
        "action": "move_to",
        "to": [
          42,
          13
        ]
      }
    ],
    "99": [
      {
        "action": "move_to",
        "to": [
          41,
          14
        ]
      }
    ],
    "100": [
      {
        "action": "move_to",
        "to": [
          40,
          15
        ]
      }
    ],
    "101": [
      {
        "action": "build",
        "at": [
          39,
          15
        ]
      },
      {
        "action": "move_to",
        "to": [
          39,
          15
        ]
      }
    ],
    "102": [
      {
        "action": "build",
        "at": [
          38,
          15
        ]
      }
    ],
    "103": [
      {
        "action": "move_to",
        "to": [
          40,
          15
        ]
      }
    ],
    "104": [
      {
        "action": "move_to",
        "to": [
          41,
          14
        ]
      }
    ],
    "105": [
      {
        "action": "move_to",
        "to": [
          42,
          13
        ]
      }
    ],
    "106": [
      {
        "action": "move_to",
        "to": [
          41,
          12
        ]
      }
    ],
    "107": [
      {
        "action": "move_to",
        "to": [
          41,
          11
        ]
      }
    ],
    "108": [
      {
        "action": "move_to",
        "to": [
          41,
          10
        ]
      }
    ],
    "109": [
      {
        "action": "move_to",
        "to": [
          40,
          9
        ]
      }
    ],
    "110": [
      {
        "action": "move_to",
        "to": [
          39,
          8
        ]
      }
    ],
    "111": [
      {
        "action": "build",
        "at": [
          39,
          7
        ]
      }
    ],
    "112": [
      {
        "action": "move_to",
        "to": [
          39,
          7
        ]
      }
    ],
    "113": [
      {
        "action": "build",
        "at": [
          40,
          6
        ]
      }
    ],
    "114": [
      {
        "action": "move_to",
        "to": [
          40,
          6
        ]
      }
    ],
    "115": [
      {
        "action": "build",
        "at": [
          41,
          5
        ]
      }
    ],
    "116": [
      {
        "action": "move_to",
        "to": [
          41,
          5
        ]
      }
    ],
    "117": [
      {
        "action": "build",
        "at": [
          41,
          4
        ]
      }
    ],
    "118": [
      {
        "action": "move_to",
        "to": [
          40,
          6
        ]
      }
    ],
    "119": [
      {
        "action": "move_to",
        "to": [
          39,
          6
        ]
      }
    ],
    "120": [
      {
        "action": "build",
        "at": [
          38,
          7
        ]
      }
    ],
    "121": [
      {
        "action": "move_to",
        "to": [
          38,
          6
        ]
      }
    ],
    "122": [
      {
        "action": "build",
        "at": [
          37,
          7
        ]
      }
    ],
    "123": [
      {
        "action": "move_to",
        "to": [
          39,
          6
        ]
      }
    ],
    "124": [
      {
        "action": "move_to",
        "to": [
          40,
          6
        ]
      }
    ],
    "125": [
      {
        "action": "move_to",
        "to": [
          41,
          5
        ]
      }
    ],
    "126": [
      {
        "action": "build",
        "at": [
          42,
          4
        ]
      }
    ],
    "127": [
      {
        "action": "move_to",
        "to": [
          40,
          6
        ]
      }
    ],
    "128": [
      {
        "action": "move_to",
        "to": [
          39,
          7
        ]
      }
    ],
    "129": [
      {
        "action": "move_to",
        "to": [
          39,
          8
        ]
      }
    ],
    "130": [
      {
        "action": "move_to",
        "to": [
          40,
          9
        ]
      }
    ],
    "131": [
      {
        "action": "move_to",
        "to": [
          41,
          10
        ]
      }
    ],
    "132": [
      {
        "action": "move_to",
        "to": [
          41,
          11
        ]
      }
    ],
    "133": [
      {
        "action": "move_to",
        "to": [
          41,
          12
        ]
      }
    ],
    "134": [
      {
        "action": "move_to",
        "to": [
          42,
          13
        ]
      }
    ],
    "135": [
      {
        "action": "move_to",
        "to": [
          41,
          14
        ]
      }
    ],
    "136": [
      {
        "action": "move_to",
        "to": [
          40,
          15
        ]
      }
    ],
    "137": [
      {
        "action": "build",
        "at": [
          40,
          16
        ]
      }
    ],
    "138": [
      {
        "action": "move_to",
        "to": [
          39,
          15
        ]
      }
    ],
    "139": [
      {
        "action": "build",
        "at": [
          38,
          16
        ]
      }
    ],
    "140": [
      {
        "action": "move_to",
        "to": [
          40,
          15
        ]
      }
    ],
    "141": [
      {
        "action": "move_to",
        "to": [
          41,
          14
        ]
      }
    ],
    "142": [
      {
        "action": "move_to",
        "to": [
          42,
          13
        ]
      }
    ],
    "143": [
      {
        "action": "move_to",
        "to": [
          41,
          12
        ]
      }
    ],
    "144": [
      {
        "action": "move_to",
        "to": [
          41,
          11
        ]
      }
    ],
    "145": [
      {
        "action": "move_to",
        "to": [
          41,
          10
        ]
      }
    ],
    "146": [
      {
        "action": "move_to",
        "to": [
          40,
          9
        ]
      }
    ],
    "147": [
      {
        "action": "move_to",
        "to": [
          39,
          8
        ]
      }
    ],
    "148": [
      {
        "action": "move_to",
        "to": [
          39,
          7
        ]
      }
    ],
    "149": [
      {
        "action": "move_to",
        "to": [
          40,
          6
        ]
      }
    ],
    "150": [
      {
        "action": "move_to",
        "to": [
          41,
          5
        ]
      }
    ],
    "151": [
      {
        "action": "build",
        "at": [
          42,
          5
        ]
      }
    ],
    "152": [
      {
        "action": "move_to",
        "to": [
          40,
          6
        ]
      }
    ],
    "153": [
      {
        "action": "move_to",
        "to": [
          39,
          7
        ]
      }
    ],
    "154": [
      {
        "action": "move_to",
        "to": [
          39,
          8
        ]
      }
    ],
    "155": [
      {
        "action": "move_to",
        "to": [
          40,
          9
        ]
      }
    ],
    "156": [
      {
        "action": "move_to",
        "to": [
          41,
          10
        ]
      }
    ],
    "157": [
      {
        "action": "move_to",
        "to": [
          41,
          11
        ]
      }
    ],
    "158": [
      {
        "action": "move_to",
        "to": [
          41,
          12
        ]
      }
    ],
    "159": [
      {
        "action": "move_to",
        "to": [
          42,
          13
        ]
      }
    ],
    "160": [
      {
        "action": "move_to",
        "to": [
          41,
          14
        ]
      }
    ],
    "161": [
      {
        "action": "move_to",
        "to": [
          40,
          15
        ]
      }
    ],
    "162": [
      {
        "action": "build",
        "at": [
          41,
          16
        ]
      }
    ],
    "163": [
      {
        "action": "move_to",
        "to": [
          40,
          16
        ]
      }
    ],
    "164": [
      {
        "action": "build",
        "at": [
          40,
          17
        ]
      }
    ],
    "165": [
      {
        "action": "move_to",
        "to": [
          39,
          15
        ]
      }
    ],
    "166": [
      {
        "action": "move_to",
        "to": [
          38,
          15
        ]
      }
    ],
    "167": [
      {
        "action": "build",
        "at": [
          37,
          16
        ]
      }
    ],
    "168": [
      {
        "action": "move_to",
        "to": [
          38,
          16
        ]
      }
    ],
    "169": [
      {
        "action": "build",
        "at": [
          38,
          17
        ]
      }
    ],
    "170": [
      {
        "action": "move_to",
        "to": [
          39,
          15
        ]
      }
    ],
    "171": [
      {
        "action": "destroy",
        "at": [
          40,
          15
        ]
      }
    ],
    "172": [
      {
        "action": "move_to",
        "to": [
          40,
          16
        ]
      }
    ],
    "173": [
      {
        "action": "move_to",
        "to": [
          41,
          17
        ]
      }
    ],
    "174": [
      {
        "action": "move_to",
        "to": [
          40,
          18
        ]
      }
    ],
    "175": [
      {
        "action": "move_to",
        "to": [
          41,
          19
        ]
      }
    ],
    "176": [
      {
        "action": "destroy",
        "at": [
          41,
          20
        ]
      }
    ],
    "177": [
      {
        "action": "move_to",
        "to": [
          40,
          18
        ]
      }
    ],
    "178": [
      {
        "action": "destroy",
        "at": [
          41,
          19
        ]
      }
    ],
    "179": [
      {
        "action": "move_to",
        "to": [
          41,
          17
        ]
      }
    ],
    "180": [
      {
        "action": "move_to",
        "to": [
          42,
          16
        ]
      }
    ],
    "181": [
      {
        "action": "move_to",
        "to": [
          42,
          15
        ]
      }
    ],
    "182": [
      {
        "action": "move_to",
        "to": [
          41,
          14
        ]
      }
    ],
    "183": [
      {
        "action": "move_to",
        "to": [
          42,
          13
        ]
      }
    ],
    "184": [
      {
        "action": "destroy",
        "at": [
          41,
          12
        ]
      }
    ],
    "185": [
      {
        "action": "move_to",
        "to": [
          41,
          14
        ]
      }
    ],
    "186": [
      {
        "action": "move_to",
        "to": [
          42,
          15
        ]
      }
    ],
    "187": [
      {
        "action": "move_to",
        "to": [
          42,
          16
        ]
      }
    ],
    "188": [
      {
        "action": "move_to",
        "to": [
          41,
          17
        ]
      }
    ],
    "189": [
      {
        "action": "destroy",
        "at": [
          40,
          18
        ]
      }
    ],
    "190": [
      {
        "action": "move_to",
        "to": [
          42,
          16
        ]
      }
    ],
    "191": [
      {
        "action": "move_to",
        "to": [
          42,
          15
        ]
      }
    ],
    "192": [
      {
        "action": "destroy",
        "at": [
          41,
          14
        ]
      }
    ],
    "193": [
      {
        "action": "move_to",
        "to": [
          42,
          16
        ]
      }
    ],
    "194": [
      {
        "action": "destroy",
        "at": [
          41,
          17
        ]
      }
    ],
    "195": [
      {
        "action": "move_to",
        "to": [
          42,
          15
        ]
      }
    ],
    "196": [
      {
        "action": "destroy",
        "at": [
          42,
          16
        ]
      }
    ]
  }
}
